{"timestamp": "2025-03-31T10:11:52.629082", "data": {"available": true, "season": 2024, "fixtures": {"played": 39, "wins": 10, "draws": 12, "losses": 17}, "goals": {"for": {"total": 45, "average": "1.2", "minute_distribution": {"0-15": {"total": 6, "percentage": "12.50%"}, "16-30": {"total": 10, "percentage": "20.83%"}, "31-45": {"total": 6, "percentage": "12.50%"}, "46-60": {"total": 13, "percentage": "27.08%"}, "61-75": {"total": 10, "percentage": "20.83%"}, "76-90": {"total": 2, "percentage": "4.17%"}, "91-105": {"total": 1, "percentage": "2.08%"}, "106-120": {"total": null, "percentage": null}}}, "against": {"total": 55, "average": "1.4", "minute_distribution": {"0-15": {"total": 10, "percentage": "19.23%"}, "16-30": {"total": 7, "percentage": "13.46%"}, "31-45": {"total": 4, "percentage": "7.69%"}, "46-60": {"total": 9, "percentage": "17.31%"}, "61-75": {"total": 8, "percentage": "15.38%"}, "76-90": {"total": 10, "percentage": "19.23%"}, "91-105": {"total": 4, "percentage": "7.69%"}, "106-120": {"total": null, "percentage": null}}}}, "home": {"played": 19, "wins": 5, "draws": 9, "losses": 5, "goals_for": 24, "goals_against": 22}, "away": {"played": 20, "wins": 5, "draws": 3, "losses": 12, "goals_for": 21, "goals_against": 33}, "clean_sheets": {"total": 0, "home": 0, "away": 0}, "failed_to_score": {"total": 12, "home": 7, "away": 5}, "penalty": {"scored": 3, "missed": 0}, "cards": {"yellow": {"0-15": {"total": 5, "percentage": "4.50%"}, "16-30": {"total": 9, "percentage": "8.11%"}, "31-45": {"total": 18, "percentage": "16.22%"}, "46-60": {"total": 19, "percentage": "17.12%"}, "61-75": {"total": 20, "percentage": "18.02%"}, "76-90": {"total": 26, "percentage": "23.42%"}, "91-105": {"total": 14, "percentage": "12.61%"}, "106-120": {"total": null, "percentage": null}}, "red": {"0-15": {"total": null, "percentage": null}, "16-30": {"total": null, "percentage": null}, "31-45": {"total": null, "percentage": null}, "46-60": {"total": null, "percentage": null}, "61-75": {"total": null, "percentage": null}, "76-90": {"total": null, "percentage": null}, "91-105": {"total": 1, "percentage": "100.00%"}, "106-120": {"total": null, "percentage": null}}}, "form": "LDLDLLDLWWWLDWDDLLDLLWWLWDLDLLLWLWLWDDD", "biggest": {"streak": {"wins": 3, "draws": 2, "losses": 3}, "wins": {"home": "5-0", "away": "0-3"}, "losses": {"home": "0-3", "away": "5-2"}, "goals": {"for": 0, "against": 0}}, "metrics": {"points_per_game": 1.0769230769230769, "goals_per_game": 1.1538461538461537, "goals_against_per_game": 1.4102564102564104, "clean_sheet_percentage": 0.0, "scoring_rate": 69.23076923076923}}}