{"timestamp": "2025-03-31T10:11:41.163240", "data": {"h2h_factor": 0.2, "stats": {"team1_wins": 1, "team2_wins": 0, "draws": 2, "total_matches": 3, "avg_team1_goals": 0.6666666666666666, "avg_team2_goals": 0.3333333333333333}, "analysis": {"weighted_dominance": 0.3333333333333333, "recent_dominance": 0.3333333333333333, "overall_dominance": 0.3333333333333333, "result_consistency": 0.0, "venue_advantage": 0.0}, "trends": {"goal_differences": [0, 1, 0], "match_dominance": [0.5, 1, 0.5], "recent_matches": [{"date": "2024-12-14T12:30:00+00:00", "team1_goals": 0, "team2_goals": 0, "venue": "away", "goal_difference": 0, "dominance": 0.5}, {"date": "2024-02-17T15:00:00+00:00", "team1_goals": 2, "team2_goals": 1, "venue": "away", "goal_difference": 1, "dominance": 1}, {"date": "2023-10-28T14:00:00+00:00", "team1_goals": 0, "team2_goals": 0, "venue": "home", "goal_difference": 0, "dominance": 0.5}]}, "confidence": "medium", "matches_analyzed": 3}}